ethcloud/__init__.py
ethcloud/__main__.py
ethcloud/cli.py
ethcloud/config.py
ethcloud/constants.py
ethcloud/core.py
ethcloud/decorators.py
ethcloud/errors.py
ethcloud/geth.py
ethcloud/provider/__init__.py
ethcloud/provider/aws.py
ethcloud/provider/base.py
ethcloud/provision/__init__.py
ethcloud/provision/ansible.cfg
ethcloud/provision/delete.yml
ethcloud/provision/inventory
ethcloud/provision/launch.yml
ethcloud/provision/provision.yml
ethcloud/provision/requirements.yml
ethcloud/provision/__pycache__/__init__.cpython-36.pyc
ethcloud/provision/roles/geth-ethereum/README.md
ethcloud/provision/roles/geth-ethereum/defaults/main.yml
ethcloud/provision/roles/geth-ethereum/handlers/main.yml
ethcloud/provision/roles/geth-ethereum/meta/main.yml
ethcloud/provision/roles/geth-ethereum/tasks/ethereum.yml
ethcloud/provision/roles/geth-ethereum/tasks/main.yml
ethcloud/provision/roles/geth-ethereum/templates/geth.service.j2
ethcloud/provision/roles/geth-ethereum/tests/inventory
ethcloud/provision/roles/geth-ethereum/tests/test.yml
ethcloud/provision/roles/geth-ethereum/vars/main.yml
ethcloud/provision/roles/iam-instance-profile/README.md
ethcloud/provision/roles/iam-instance-profile/defaults/main.yml
ethcloud/provision/roles/iam-instance-profile/handlers/main.yml
ethcloud/provision/roles/iam-instance-profile/meta/main.yml
ethcloud/provision/roles/iam-instance-profile/tasks/iam_instance_profile.yml
ethcloud/provision/roles/iam-instance-profile/tasks/main.yml
ethcloud/provision/roles/iam-instance-profile/tests/inventory
ethcloud/provision/roles/iam-instance-profile/tests/test.yml
ethcloud/provision/roles/iam-instance-profile/vars/main.yml
ethcloud/provision/roles/journald-cloudwatch/README.md
ethcloud/provision/roles/journald-cloudwatch/defaults/main.yml
ethcloud/provision/roles/journald-cloudwatch/handlers/main.yml
ethcloud/provision/roles/journald-cloudwatch/meta/main.yml
ethcloud-0.2.1.dist-info/DESCRIPTION.rst
ethcloud-0.2.1.dist-info/METADATA
ethcloud-0.2.1.dist-info/RECORD
ethcloud-0.2.1.dist-info/WHEEL
ethcloud-0.2.1.dist-info/entry_points.txt
ethcloud-0.2.1.dist-info/metadata.json
ethcloud-0.2.1.dist-info/top_level.txt
