Metadata-Version: 2.0
Name: ethcloud
Version: 0.2.1
Summary: A cli tool too launch, manage and use ethereum client on the cloud
Home-page: https://github.com/kgritesh/ethcloud
Author: Ritesh Kadmawala
Author-email: k.g.ritesh@gmail.com
License: MIT
Platform: any
Classifier: Development Status :: 4 - Beta
Classifier: Environment :: Console
Classifier: Intended Audience :: Developers
Classifier: License :: OSI Approved :: MIT License
Classifier: Operating System :: POSIX
Classifier: Operating System :: MacOS
Classifier: Operating System :: Unix
Classifier: Operating System :: Microsoft :: Windows
Classifier: Programming Language :: Python
Classifier: Programming Language :: Python :: 2.7
Classifier: Programming Language :: Python :: 3
Classifier: Programming Language :: Python :: 3.4
Classifier: Programming Language :: Python :: 3.5
Classifier: Programming Language :: Python :: 3.6
Classifier: Topic :: Software Development :: Libraries :: Python Modules
Requires-Dist: PyYaml
Requires-Dist: ansible
Requires-Dist: attrdict
Requires-Dist: boto3
Requires-Dist: click
